{
  "schema_version": "1.0",
  "build": {
    "generated_at": "2026-04-10",
    "source_version": "8.4",
    "warnings": [],
    "notes": "Added ability_dict_J (Crow Court stubs). Added campaign_system entry. Cleaned stale paths."
  },
  "index": [
    {
      "id": "philosophy",
      "title": "Philosophy & Design",
      "path": "rules_master.sections.philosophy",
      "type": "meta"
    },
    {
      "id": "quickstart",
      "title": "Quickstart",
      "type": "core",
      "file": "05_quickstart.json"
    },
    {
      "id": "core_mechanics",
      "title": "Core Mechanics",
      "type": "core",
      "file": "10_core_mechanics.json"
    },
    {
      "id": "core_quality",
      "title": "Quality System",
      "parent": "core_mechanics",
      "file": "10_core_mechanics.json"
    },
    {
      "id": "core_rolls",
      "title": "The Roll",
      "parent": "core_mechanics",
      "file": "10_core_mechanics.json"
    },
    {
      "id": "core_defense",
      "title": "Defense & Damage",
      "parent": "core_mechanics",
      "file": "10_core_mechanics.json"
    },
    {
      "id": "turn_structure",
      "title": "Turn Structure",
      "type": "core",
      "file": "20_turn_structure.json"
    },
    {
      "id": "activation",
      "title": "Activation Cycle",
      "parent": "turn_structure",
      "file": "20_turn_structure.json"
    },
    {
      "id": "campaign_system",
      "title": "Campaign System",
      "type": "system",
      "file": "30_campaign_system.json"
    },
    {
      "id": "visibility_vault",
      "title": "Visibility Vault",
      "type": "vault",
      "file": "30_visibility_vault.json"
    },
    {
      "id": "locomotion_vault",
      "title": "Locomotion Vault",
      "type": "vault",
      "file": "40_locomotion_vault.json"
    },
    {
      "id": "combat_vault",
      "title": "Combat Vault",
      "type": "vault",
      "file": "50_combat_vault.json"
    },
    {
      "id": "morale_vault",
      "title": "Morale Vault",
      "type": "vault",
      "file": "60_morale_vault.json"
    },
    {
      "id": "unit_identities",
      "title": "Unit Identities",
      "type": "system",
      "file": "70_unit_identities.json"
    },
    {
      "id": "ability_engine",
      "title": "Ability Engine",
      "type": "system",
      "file": "80_ability_engine.json"
    },
    {
      "id": "ability_dict_A",
      "title": "Ability Dictionary – A",
      "type": "abilities",
      "file": "90_ability_dictionary_A.json"
    },
    {
      "id": "ability_dict_B",
      "title": "Ability Dictionary – B",
      "type": "abilities",
      "file": "91_ability_dictionary_B.json"
    },
    {
      "id": "ability_dict_C",
      "title": "Ability Dictionary – C",
      "type": "abilities",
      "file": "92_ability_dictionary_C.json"
    },
    {
      "id": "ability_dict_D",
      "title": "Ability Dictionary – D",
      "type": "abilities",
      "file": "93_ability_dictionary_D.json"
    },
    {
      "id": "ability_dict_E",
      "title": "Ability Dictionary – E",
      "type": "abilities",
      "file": "94_ability_dictionary_E.json"
    },
    {
      "id": "ability_dict_F",
      "title": "Ability Dictionary – F",
      "type": "abilities",
      "file": "95_ability_dictionary_F.json"
    },
    {
      "id": "ability_dict_G",
      "title": "Ability Dictionary – G",
      "type": "abilities",
      "file": "96_ability_dictionary_G.json"
    },
    {
      "id": "ability_dict_H",
      "title": "Ability Dictionary – H",
      "type": "abilities",
      "file": "97_ability_dictionary_H.json"
    },
    {
      "id": "ability_dict_I",
      "title": "Ability Dictionary – I",
      "type": "abilities",
      "file": "98_ability_dictionary_I.json"
    },
    {
      "id": "ability_dict_J",
      "title": "Ability Dictionary – J (Crow Court)",
      "type": "abilities",
      "file": "99_ability_dictionary_J.json"
    },
    {
      "id": "weapon_properties",
      "title": "Weapon Properties",
      "type": "system",
      "file": "100_weapon_properties.json"
    },
    {
      "id": "wild_magic",
      "title": "Wild Magic Table",
      "type": "system",
      "file": "100_wild_magic_table.json"
    },
    {
      "id": "terrain_vault",
      "title": "Terrain Vault",
      "type": "vault",
      "file": "120_terrain_vault.json"
    },
    {
      "id": "objective_vault",
      "title": "Objective Vault",
      "type": "vault",
      "file": "240_objective_vault.json"
    },
    {
      "id": "scenario_vault",
      "title": "Scenario Vault",
      "type": "vault",
      "file": "140_scenario_vault.json"
    },
    {
      "id": "location_types",
      "title": "Location Types",
      "type": "system",
      "file": "150_location_types.json"
    },
    {
      "id": "location_vault",
      "title": "Location Vault",
      "type": "vault",
      "file": "150_location_vault.json"
    },
    {
      "id": "named_locations",
      "title": "Named Locations",
      "type": "vault",
      "file": "170_named_locations.json"
    }
  ],
  "rules_master": {
    "version": "8.3",
    "last_updated": "2026-04-10",
    "changelog": "Added ability_dict_J for Crow Court abilities. Added campaign_system to index. Previous: Removed variable (X) notation. Implemented consistent Brutal/Savage progression for offensive abilities. Standardized ranges to 3\"/6\"/12\". Simplified Blast, Fear, Pierce, Impact, and Tough naming.",
    "sections": {
      "philosophy": "The 'Flavor Vault'. High-level tenets and the 'Fast Resolution' handshake.",
      "core_mechanics": "The math: Quality rolls, Successes, Defense calculations, and the Death Spiral.",
      "dice_manipulation": "Lucky Breaks, Natural Sixes, and Critical Failures.",
      "turn_structure": "Initiative, Activation cycles, and Action types (Simple vs. Complex).",
      "campaign_system": "Campaign rules: Silver economy, injuries, advancement, and between-game progression.",
      "locomotion_and_visibility": "Movement speeds, Terrain types, Line of Sight, and Cover logic.",
      "combat_and_damage": "Melee vs. Ranged, Automatic Damage sources, and Weapon Tags.",
      "morale_and_status": "Shaken, Panicked, Fear Cascades, and Condition removal.",
      "unit_identities": "The 8 Core Archetypes (Grunt, Titan, etc.) and their passive logic.",
      "ability_dictionary": "The Universal Library of keywords (Stealth, Tough, Repair, etc.).",
      "weapon_properties": "Weapon tags and special effects that modify attacks.",
      "wild_magic_table": "Thyr-powered mystical effects and consequences.",
      "timing_and_engine": "Once per Activation/Round/Game and Ability Priority.",
      "unit_variant_logic": "How the app handles 'Chassis' modifications (Baby vs. Mama)."
    }
  }
}
